dglog/__init__.py
dglog/py.typed
dglog-1.0.0.1.dist-info/licenses/LICENSE
dglog-1.0.0.1.dist-info/METADATA
dglog-1.0.0.1.dist-info/WHEEL
dglog-1.0.0.1.dist-info/top_level.txt
dglog-1.0.0.1.dist-info/RECORD
