Metadata-Version: 2.4
Name: dglog
Version: 1.0.0.1
Summary: Advanced configurable logger for Python with file rotation and CLI support
Home-page: https://gitlab.com/gng-group/dglog.git
Author: Malanris
Author-email: Roman Rasputin <admin@roro.su>
License: MIT License
Project-URL: Homepage, https://gitlab.com/gng-group/dglog
Project-URL: BugTracker, https://gitlab.com/gng-group/dglog/issues
Keywords: logging,logger,rotation,timed,advanced
Classifier: Development Status :: 4 - Beta
Classifier: Intended Audience :: Developers
Classifier: License :: OSI Approved :: MIT License
Classifier: Programming Language :: Python :: 3
Classifier: Programming Language :: Python :: 3.7
Classifier: Programming Language :: Python :: 3.8
Classifier: Programming Language :: Python :: 3.9
Classifier: Programming Language :: Python :: 3.10
Classifier: Programming Language :: Python :: 3.11
Classifier: Operating System :: OS Independent
Classifier: Topic :: Software Development :: Libraries :: Python Modules
Classifier: Topic :: System :: Logging
Requires-Python: >=3.7
License-File: LICENSE
Dynamic: author
Dynamic: home-page
Dynamic: license-file
